mirage_database_service/__init__.py
mirage_database_service/domain_controller.py
mirage_database_service-0.5.0.dist-info/METADATA
mirage_database_service-0.5.0.dist-info/WHEEL
mirage_database_service-0.5.0.dist-info/top_level.txt
mirage_database_service-0.5.0.dist-info/RECORD
