Metadata-Version: 2.1
Name: mirage_database_service
Version: 0.5.0
Summary: A brief description of your package
Author-email: Rystad Energy General Software <gsw@rystadenergy.com>
Project-URL: homepage, https://dev.azure.com/RE-Technology/Mirage/_git/MirageDatabaseService
Project-URL: repository, https://dev.azure.com/RE-Technology/Mirage/_git/MirageDatabaseService
Project-URL: documentation, https://dev.azure.com/RE-Technology/Mirage/_git/MirageDatabaseService
Requires-Dist: requests>=2.25.1
